{
  "date": "October 1, 2023", 
  "fetch_info": {
    "duration": 22.0850670337677, 
    "end_date": "2023-10-01T08:01:01.738458", 
    "lang": "en", 
    "start_date": "2023-09-24T08:01:01.738458"
  }, 
  "full_lang_name": "English", 
  "mainspace": [
    {
      "edits": 1469, 
      "page_id": 70308452, 
      "rev_ids": {
        "new": 1178046748, 
        "old": 1176834136
      }, 
      "title": "India_at_the_2022_Asian_Games", 
      "title_s": "India at the 2022 Asian Games", 
      "users": 139
    }, 
    {
      "edits": 541, 
      "page_id": 74897876, 
      "rev_ids": {
        "new": 1178030378, 
        "old": 1176873999
      }, 
      "title": "Banjska_attack", 
      "title_s": "Banjska attack", 
      "users": 74
    }, 
    {
      "edits": 478, 
      "page_id": 72389466, 
      "rev_ids": {
        "new": 1178043849, 
        "old": 1176833156
      }, 
      "title": "Deaths_in_2023", 
      "title_s": "Deaths in 2023", 
      "users": 82
    }, 
    {
      "edits": 444, 
      "page_id": 74857564, 
      "rev_ids": {
        "new": 1178035912, 
        "old": 1176831502
      }, 
      "title": "2023_Azerbaijani_offensive_in_Nagorno-Karabakh", 
      "title_s": "2023 Azerbaijani offensive in Nagorno-Karabakh", 
      "users": 58
    }, 
    {
      "edits": 430, 
      "page_id": 70921929, 
      "rev_ids": {
        "new": 1178044816, 
        "old": 1176833316
      }, 
      "title": "Indonesia_at_the_2022_Asian_Games", 
      "title_s": "Indonesia at the 2022 Asian Games", 
      "users": 42
    }, 
    {
      "edits": 366, 
      "page_id": 74894347, 
      "rev_ids": {
        "new": 1178044643, 
        "old": 1176820970
      }, 
      "title": "2022_Asian_Games_medal_table", 
      "title_s": "2022 Asian Games medal table", 
      "users": 96
    }, 
    {
      "edits": 366, 
      "page_id": 73600019, 
      "rev_ids": {
        "new": 1178032089, 
        "old": 1176793987
      }, 
      "title": "Endorsements_in_the_2023_Australian_Indigenous_Voice_referendum", 
      "title_s": "Endorsements in the 2023 Australian Indigenous Voice referendum", 
      "users": 23
    }, 
    {
      "edits": 358, 
      "page_id": 70138526, 
      "rev_ids": {
        "new": 1178040237, 
        "old": 1176833315
      }, 
      "title": "Malaysia_at_the_2022_Asian_Games", 
      "title_s": "Malaysia at the 2022 Asian Games", 
      "users": 26
    }, 
    {
      "edits": 343, 
      "page_id": 16897729, 
      "rev_ids": {
        "new": 1177930635, 
        "old": 1168260396
      }, 
      "title": "Kang_Full", 
      "title_s": "Kang Full", 
      "users": 7
    }, 
    {
      "edits": 341, 
      "page_id": 74462172, 
      "rev_ids": {
        "new": 1178046355, 
        "old": 1176796892
      }, 
      "title": "Football_at_the_2022_Asian_Games_\u2013_Men's_tournament", 
      "title_s": "Football at the 2022 Asian Games \u2013 Men's tournament", 
      "users": 96
    }, 
    {
      "edits": 328, 
      "page_id": 74864425, 
      "rev_ids": {
        "new": 1178036625, 
        "old": 1176829643
      }, 
      "title": "Iran_at_the_2022_Asian_Games", 
      "title_s": "Iran at the 2022 Asian Games", 
      "users": 37
    }, 
    {
      "edits": 323, 
      "page_id": 30471447, 
      "rev_ids": {
        "new": 1178035522, 
        "old": 1176827737
      }, 
      "title": "Luttra_Woman", 
      "title_s": "Luttra Woman", 
      "users": 2
    }, 
    {
      "edits": 299, 
      "page_id": 67345956, 
      "rev_ids": {
        "new": 1178038274, 
        "old": 1176799322
      }, 
      "title": "Saw_X", 
      "title_s": "Saw X", 
      "users": 110
    }, 
    {
      "edits": 294, 
      "page_id": 74184147, 
      "rev_ids": {
        "new": 1178043622, 
        "old": 1176828199
      }, 
      "title": "E.A.T._(TV_program)", 
      "title_s": "E.A.T. (TV program)", 
      "users": 21
    }, 
    {
      "edits": 285, 
      "page_id": 74922032, 
      "rev_ids": {
        "new": 1178029438, 
        "old": 1177383519
      }, 
      "title": "Flight_of_Nagorno-Karabakh_Armenians", 
      "title_s": "Flight of Nagorno-Karabakh Armenians", 
      "users": 58
    }, 
    {
      "edits": 276, 
      "page_id": 70138530, 
      "rev_ids": {
        "new": 1178037880, 
        "old": 1176833840
      }, 
      "title": "Philippines_at_the_2022_Asian_Games", 
      "title_s": "Philippines at the 2022 Asian Games", 
      "users": 24
    }, 
    {
      "edits": 261, 
      "page_id": 74555962, 
      "rev_ids": {
        "new": 1178043368, 
        "old": 1176676256
      }, 
      "title": "2023_British_Open", 
      "title_s": "2023 British Open", 
      "users": 24
    }, 
    {
      "edits": 249, 
      "page_id": 61335443, 
      "rev_ids": {
        "new": 1178032270, 
        "old": 1176760254
      }, 
      "title": "2023_Cricket_World_Cup_squads", 
      "title_s": "2023 Cricket World Cup squads", 
      "users": 32
    }, 
    {
      "edits": 235, 
      "page_id": 70222680, 
      "rev_ids": {
        "new": 1177978055, 
        "old": 1176832995
      }, 
      "title": "Tiger_3", 
      "title_s": "Tiger 3", 
      "users": 63
    }, 
    {
      "edits": 234, 
      "page_id": 74461006, 
      "rev_ids": {
        "new": 1178046168, 
        "old": 1176832024
      }, 
      "title": "Football_at_the_2022_Asian_Games_\u2013_Women's_tournament", 
      "title_s": "Football at the 2022 Asian Games \u2013 Women's tournament", 
      "users": 50
    }
  ], 
  "new_articles": [
    {
      "edits": 285, 
      "page_id": 74922032, 
      "rev_ids": {
        "new": 1178029438, 
        "old": 1177383519
      }, 
      "title": "Flight_of_Nagorno-Karabakh_Armenians", 
      "title_s": "Flight of Nagorno-Karabakh Armenians", 
      "users": 58
    }, 
    {
      "edits": 221, 
      "page_id": 74902353, 
      "rev_ids": {
        "new": 1178030538, 
        "old": 1176955301
      }, 
      "title": "Yaroslav_Hunka", 
      "title_s": "Yaroslav Hunka", 
      "users": 83
    }, 
    {
      "edits": 181, 
      "page_id": 74897658, 
      "rev_ids": {
        "new": 1178046170, 
        "old": 1176858617
      }, 
      "title": "Thailand_at_the_2022_Asian_Games", 
      "title_s": "Thailand at the 2022 Asian Games", 
      "users": 16
    }, 
    {
      "edits": 165, 
      "page_id": 74931029, 
      "rev_ids": {
        "new": 1177957447, 
        "old": 1177623437
      }, 
      "title": "2023_Rotterdam_shootings", 
      "title_s": "2023 Rotterdam shootings", 
      "users": 41
    }, 
    {
      "edits": 160, 
      "page_id": 74919453, 
      "rev_ids": {
        "new": 1178032081, 
        "old": 1177275773
      }, 
      "title": "Qaraqosh_wedding_fire", 
      "title_s": "Qaraqosh wedding fire", 
      "users": 51
    }, 
    {
      "edits": 153, 
      "page_id": 74912015, 
      "rev_ids": {
        "new": 1177945250, 
        "old": 1177131602
      }, 
      "title": "Plaza_San_Diego_Viejo", 
      "title_s": "Plaza San Diego Viejo", 
      "users": 5
    }, 
    {
      "edits": 135, 
      "page_id": 74936775, 
      "rev_ids": {
        "new": 1178044694, 
        "old": 1177741200
      }, 
      "title": "2023_Mastung_bombing", 
      "title_s": "2023 Mastung bombing", 
      "users": 45
    }, 
    {
      "edits": 132, 
      "page_id": 74900199, 
      "rev_ids": {
        "new": 1177986068, 
        "old": 1176906668
      }, 
      "title": "Bible_Names_in_their_Native_Languages", 
      "title_s": "Bible Names in their Native Languages", 
      "users": 6
    }, 
    {
      "edits": 131, 
      "page_id": 74930345, 
      "rev_ids": {
        "new": 1178023218, 
        "old": 1177609257
      }, 
      "title": "The_Alpinist", 
      "title_s": "The Alpinist", 
      "users": 5
    }, 
    {
      "edits": 131, 
      "page_id": 74900239, 
      "rev_ids": {
        "new": 1178033865, 
        "old": 1176907712
      }, 
      "title": "Miss_Universe_2024", 
      "title_s": "Miss Universe 2024", 
      "users": 40
    }
  ], 
  "short_lang_name": "en", 
  "stats": {
    "anon_edits": 131118, 
    "anon_ip_count": 51426, 
    "anon_titles": 66599, 
    "bot_count": 43, 
    "bot_edits": 187328, 
    "bot_titles": 172298, 
    "edits": 859188, 
    "titles": 438821, 
    "total_users": 141556, 
    "users": 90130
  }, 
  "talk_stats": {
    "anon_edits": 4976, 
    "anon_ip_count": 3289, 
    "anon_titles": 3176, 
    "bot_count": 28, 
    "bot_edits": 7718, 
    "bot_titles": 6883, 
    "edits": 53072, 
    "titles": 29478, 
    "total_users": 12005, 
    "users": 8716
  }, 
  "talkspace": [
    {
      "edits": 310, 
      "page_id": 74922487, 
      "rev_ids": {
        "new": 1178023649, 
        "old": 1177422467
      }, 
      "title": "Exodus_of_Armenians_from_Nagorno-Karabakh", 
      "title_s": "Exodus of Armenians from Nagorno-Karabakh", 
      "users": 42
    }, 
    {
      "edits": 292, 
      "page_id": 74857581, 
      "rev_ids": {
        "new": 1178045649, 
        "old": 1176827834
      }, 
      "title": "2023_Nagorno-Karabakh_clashes", 
      "title_s": "2023 Nagorno-Karabakh clashes", 
      "users": 49
    }, 
    {
      "edits": 274, 
      "page_id": 66692278, 
      "rev_ids": {
        "new": 1178043307, 
        "old": 1176815883
      }, 
      "title": "COVID-19_lab_leak_theory", 
      "title_s": "COVID-19 lab leak theory", 
      "users": 41
    }, 
    {
      "edits": 244, 
      "page_id": 74902452, 
      "rev_ids": {
        "new": 1178006250, 
        "old": 1176956998
      }, 
      "title": "Yaroslav_Hunka", 
      "title_s": "Yaroslav Hunka", 
      "users": 95
    }, 
    {
      "edits": 217, 
      "page_id": 70149877, 
      "rev_ids": {
        "new": 1178043103, 
        "old": 1176833331
      }, 
      "title": "Russian_invasion_of_Ukraine", 
      "title_s": "Russian invasion of Ukraine", 
      "users": 20
    }
  ]
}