{
  "date": "December 2, 2019", 
  "fetch_info": {
    "duration": 22.22833013534546, 
    "end_date": "2019-12-02T13:00:11.149184", 
    "lang": "ko", 
    "start_date": "2019-11-25T13:00:11.149184"
  }, 
  "full_lang_name": "Korean", 
  "mainspace": [
    {
      "edits": 188, 
      "page_id": 1237756, 
      "rev_ids": {
        "new": 25293980, 
        "old": 25258636
      }, 
      "title": "\ub3d9\ubcf5_\uc624\uc528", 
      "title_s": "\ub3d9\ubcf5 \uc624\uc528", 
      "users": 4
    }, 
    {
      "edits": 120, 
      "page_id": 2353935, 
      "rev_ids": {
        "new": 25290763, 
        "old": 25255849
      }, 
      "title": "UEFA_\uc5ec\uc790_\uc720\ub85c_2021_\uc608\uc120", 
      "title_s": "UEFA \uc5ec\uc790 \uc720\ub85c 2021 \uc608\uc120", 
      "users": 3
    }, 
    {
      "edits": 90, 
      "page_id": 1881990, 
      "rev_ids": {
        "new": 25291689, 
        "old": 25260670
      }, 
      "title": "\uaca8\uc6b8\uc655\uad6d_2", 
      "title_s": "\uaca8\uc6b8\uc655\uad6d 2", 
      "users": 17
    }, 
    {
      "edits": 78, 
      "page_id": 484084, 
      "rev_ids": {
        "new": 25294290, 
        "old": 25246125
      }, 
      "title": "\uad6d\uae30_\ubaa9\ub85d", 
      "title_s": "\uad6d\uae30 \ubaa9\ub85d", 
      "users": 2
    }, 
    {
      "edits": 76, 
      "page_id": 1444341, 
      "rev_ids": {
        "new": 25294631, 
        "old": 25260915
      }, 
      "title": "\ub0e5\ucf54_\ub300\uc804\uc7c1", 
      "title_s": "\ub0e5\ucf54 \ub300\uc804\uc7c1", 
      "users": 14
    }, 
    {
      "edits": 73, 
      "page_id": 2602230, 
      "rev_ids": {
        "new": 25288876, 
        "old": 25266485
      }, 
      "title": "2019\ub144_AFC_\uc5ec\uc790_\ud074\ub7fd_\ucc54\ud53c\uc5b8\uc2ed", 
      "title_s": "2019\ub144 AFC \uc5ec\uc790 \ud074\ub7fd \ucc54\ud53c\uc5b8\uc2ed", 
      "users": 6
    }, 
    {
      "edits": 72, 
      "page_id": 175150, 
      "rev_ids": {
        "new": 25273652, 
        "old": 24326091
      }, 
      "title": "\uc77c\ubcf8\uc758_\uc5f0\ud638", 
      "title_s": "\uc77c\ubcf8\uc758 \uc5f0\ud638", 
      "users": 1
    }, 
    {
      "edits": 71, 
      "page_id": 2378024, 
      "rev_ids": {
        "new": 25293886, 
        "old": 25249555
      }, 
      "title": "2019\ub144_\ud0dc\ud48d", 
      "title_s": "2019\ub144 \ud0dc\ud48d", 
      "users": 12
    }, 
    {
      "edits": 68, 
      "page_id": 2603669, 
      "rev_ids": {
        "new": 25290388, 
        "old": 25281830
      }, 
      "title": "\uc624\uc2a4\ud2b8\ub9ac\uc544-\ud5dd\uac00\ub9ac_\uc81c\uad6d\ub839_\ubcf4\uc2a4\ub2c8\uc544_\ud5e4\ub974\uccb4\uace0\ube44\ub098", 
      "title_s": "\uc624\uc2a4\ud2b8\ub9ac\uc544-\ud5dd\uac00\ub9ac \uc81c\uad6d\ub839 \ubcf4\uc2a4\ub2c8\uc544 \ud5e4\ub974\uccb4\uace0\ube44\ub098", 
      "users": 4
    }, 
    {
      "edits": 60, 
      "page_id": 871102, 
      "rev_ids": {
        "new": 25275932, 
        "old": 25258827
      }, 
      "title": "\uc5ec\uc218\uacf5\uc5c5\uace0\ub4f1\ud559\uad50", 
      "title_s": "\uc5ec\uc218\uacf5\uc5c5\uace0\ub4f1\ud559\uad50", 
      "users": 3
    }, 
    {
      "edits": 58, 
      "page_id": 2562408, 
      "rev_ids": {
        "new": 25276570, 
        "old": 25175569
      }, 
      "title": "UEFA_\uc720\ub85c\ud30c\ub9ac\uadf8_2019-20_\uc870\ubcc4_\ub9ac\uadf8", 
      "title_s": "UEFA \uc720\ub85c\ud30c\ub9ac\uadf8 2019-20 \uc870\ubcc4 \ub9ac\uadf8", 
      "users": 2
    }, 
    {
      "edits": 55, 
      "page_id": 2467237, 
      "rev_ids": {
        "new": 25290761, 
        "old": 25254661
      }, 
      "title": "AFC_\ucc54\ud53c\uc5b8\uc2a4\ub9ac\uadf8_2020", 
      "title_s": "AFC \ucc54\ud53c\uc5b8\uc2a4\ub9ac\uadf8 2020", 
      "users": 8
    }, 
    {
      "edits": 54, 
      "page_id": 1246909, 
      "rev_ids": {
        "new": 25294624, 
        "old": 25257654
      }, 
      "title": "\ubbf8\uc2a4\ud130\ub9ac_\uc74c\uc545\uc1fc_\ubcf5\uba74\uac00\uc655", 
      "title_s": "\ubbf8\uc2a4\ud130\ub9ac \uc74c\uc545\uc1fc \ubcf5\uba74\uac00\uc655", 
      "users": 12
    }, 
    {
      "edits": 53, 
      "page_id": 240380, 
      "rev_ids": {
        "new": 25293466, 
        "old": 25258383
      }, 
      "title": "\uad6c\ud558\ub77c", 
      "title_s": "\uad6c\ud558\ub77c", 
      "users": 22
    }, 
    {
      "edits": 48, 
      "page_id": 1319202, 
      "rev_ids": {
        "new": 25294008, 
        "old": 25230868
      }, 
      "title": "\uc911\ub3c4\uc6b0\ud30c_\uc815\ub2f9_\ubaa9\ub85d", 
      "title_s": "\uc911\ub3c4\uc6b0\ud30c \uc815\ub2f9 \ubaa9\ub85d", 
      "users": 3
    }, 
    {
      "edits": 46, 
      "page_id": 2455306, 
      "rev_ids": {
        "new": 25286633, 
        "old": 25256452
      }, 
      "title": "\uc2a4\ud2b8\ub808\uc774_\ud0a4\uc988\uc758_\uc74c\ubc18_\uc678_\ud65c\ub3d9_\ubaa9\ub85d", 
      "title_s": "\uc2a4\ud2b8\ub808\uc774 \ud0a4\uc988\uc758 \uc74c\ubc18 \uc678 \ud65c\ub3d9 \ubaa9\ub85d", 
      "users": 1
    }, 
    {
      "edits": 44, 
      "page_id": 2602880, 
      "rev_ids": {
        "new": 25294298, 
        "old": 25272690
      }, 
      "title": "\uc870\uba85\uc12d", 
      "title_s": "\uc870\uba85\uc12d", 
      "users": 3
    }, 
    {
      "edits": 43, 
      "page_id": 2582365, 
      "rev_ids": {
        "new": 25294153, 
        "old": 25258547
      }, 
      "title": "\ud3ad\uc218", 
      "title_s": "\ud3ad\uc218", 
      "users": 17
    }, 
    {
      "edits": 42, 
      "page_id": 2562096, 
      "rev_ids": {
        "new": 25271897, 
        "old": 25203194
      }, 
      "title": "UEFA_\ucc54\ud53c\uc5b8\uc2a4\ub9ac\uadf8_2019-20_\uc870\ubcc4_\ub9ac\uadf8", 
      "title_s": "UEFA \ucc54\ud53c\uc5b8\uc2a4\ub9ac\uadf8 2019-20 \uc870\ubcc4 \ub9ac\uadf8", 
      "users": 1
    }, 
    {
      "edits": 42, 
      "page_id": 645527, 
      "rev_ids": {
        "new": 25292536, 
        "old": 25245367
      }, 
      "title": "JTBC", 
      "title_s": "JTBC", 
      "users": 8
    }
  ], 
  "new_articles": [
    {
      "edits": 73, 
      "page_id": 2602230, 
      "rev_ids": {
        "new": 25288876, 
        "old": 25266485
      }, 
      "title": "AFC_\uc5ec\uc790_\ud074\ub7fd_\ucc54\ud53c\uc5b8\uc2ed_2019", 
      "title_s": "AFC \uc5ec\uc790 \ud074\ub7fd \ucc54\ud53c\uc5b8\uc2ed 2019", 
      "users": 6
    }, 
    {
      "edits": 68, 
      "page_id": 2603669, 
      "rev_ids": {
        "new": 25290388, 
        "old": 25281830
      }, 
      "title": "\uc624\uc2a4\ud2b8\ub9ac\uc544-\ud5dd\uac00\ub9ac_\uc81c\uad6d\ub839_\ubcf4\uc2a4\ub2c8\uc544_\ud5e4\ub974\uccb4\uace0\ube44\ub098", 
      "title_s": "\uc624\uc2a4\ud2b8\ub9ac\uc544-\ud5dd\uac00\ub9ac \uc81c\uad6d\ub839 \ubcf4\uc2a4\ub2c8\uc544 \ud5e4\ub974\uccb4\uace0\ube44\ub098", 
      "users": 4
    }, 
    {
      "edits": 44, 
      "page_id": 2602880, 
      "rev_ids": {
        "new": 25294298, 
        "old": 25272690
      }, 
      "title": "\uc870\uba85\uc12d", 
      "title_s": "\uc870\uba85\uc12d", 
      "users": 3
    }, 
    {
      "edits": 38, 
      "page_id": 2601932, 
      "rev_ids": {
        "new": 25270748, 
        "old": 25262216
      }, 
      "title": "\uaebc\uc6b0\uc800\uc774_\uc804\ud22c", 
      "title_s": "\uaebc\uc6b0\uc800\uc774 \uc804\ud22c", 
      "users": 2
    }, 
    {
      "edits": 35, 
      "page_id": 2603137, 
      "rev_ids": {
        "new": 25277412, 
        "old": 25276299
      }, 
      "title": "\uae40\uc5f0\uc2dd(\uc11c\uc6b8\ub300\ud559\uad50_\uba85\uc608\uad50\uc218,_\uc6b4\uac15\ud559\uc6d0_\uc774\uc0ac\uc7a5)", 
      "title_s": "\uae40\uc5f0\uc2dd(\uc11c\uc6b8\ub300\ud559\uad50 \uba85\uc608\uad50\uc218, \uc6b4\uac15\ud559\uc6d0 \uc774\uc0ac\uc7a5)", 
      "users": 2
    }, 
    {
      "edits": 31, 
      "page_id": 2602619, 
      "rev_ids": {
        "new": 25290214, 
        "old": 25269208
      }, 
      "title": "Midnight_Queen", 
      "title_s": "Midnight Queen", 
      "users": 2
    }, 
    {
      "edits": 28, 
      "page_id": 2603060, 
      "rev_ids": {
        "new": 25280388, 
        "old": 25275003
      }, 
      "title": "\ubc15\ub2cc_\uc6d0\uc815", 
      "title_s": "\ubc15\ub2cc \uc6d0\uc815", 
      "users": 2
    }, 
    {
      "edits": 27, 
      "page_id": 2604382, 
      "rev_ids": {
        "new": 25291215, 
        "old": 25291005
      }, 
      "title": "\ud328\ud2b8\ub9ad_\uc81c\uc784\uc2a4_\ub9e5\uae00\ub9b0\uce58", 
      "title_s": "\ud328\ud2b8\ub9ad \uc81c\uc784\uc2a4 \ub9e5\uae00\ub9b0\uce58", 
      "users": 3
    }, 
    {
      "edits": 26, 
      "page_id": 2603607, 
      "rev_ids": {
        "new": 25293972, 
        "old": 25281028
      }, 
      "title": "\ucd08\uc774\ub77d\ucee8\ud150\uce20\ud329\ud1a0\ub9ac\uadf8\ub8f9", 
      "title_s": "\ucd08\uc774\ub77d\ucee8\ud150\uce20\ud329\ud1a0\ub9ac\uadf8\ub8f9", 
      "users": 7
    }, 
    {
      "edits": 22, 
      "page_id": 2601898, 
      "rev_ids": {
        "new": 25270738, 
        "old": 25261872
      }, 
      "title": "\uc790\uafe7-\uc798\ub7fc_\uc804\ud22c", 
      "title_s": "\uc790\uafe7-\uc798\ub7fc \uc804\ud22c", 
      "users": 2
    }
  ], 
  "short_lang_name": "ko", 
  "stats": {
    "anon_edits": 11190, 
    "anon_ip_count": 2100, 
    "anon_titles": 4449, 
    "bot_count": 22, 
    "bot_edits": 2885, 
    "bot_titles": 2483, 
    "edits": 25457, 
    "titles": 11017, 
    "total_users": 5019, 
    "users": 2919
  }, 
  "talk_stats": {
    "anon_edits": 8, 
    "anon_ip_count": 5, 
    "anon_titles": 6, 
    "bot_count": 5, 
    "bot_edits": 571, 
    "bot_titles": 566, 
    "edits": 726, 
    "titles": 608, 
    "total_users": 44, 
    "users": 39
  }, 
  "talkspace": [
    {
      "edits": 44, 
      "page_id": 2603614, 
      "rev_ids": {
        "new": 25289722, 
        "old": 25281202
      }, 
      "title": "355\uace0\uc9c0_\uc804\ud22c", 
      "title_s": "355\uace0\uc9c0 \uc804\ud22c", 
      "users": 6
    }, 
    {
      "edits": 24, 
      "page_id": 335020, 
      "rev_ids": {
        "new": 25287200, 
        "old": 22904008
      }, 
      "title": "\uc870\uc120\ub85c\ub3d9\ub2f9", 
      "title_s": "\uc870\uc120\ub85c\ub3d9\ub2f9", 
      "users": 2
    }, 
    {
      "edits": 17, 
      "page_id": 2474135, 
      "rev_ids": {
        "new": 25294383, 
        "old": 25259691
      }, 
      "title": "\ube0c\ub864\uc2a4\ud0c0\uc988", 
      "title_s": "\ube0c\ub864\uc2a4\ud0c0\uc988", 
      "users": 4
    }, 
    {
      "edits": 16, 
      "page_id": 1710231, 
      "rev_ids": {
        "new": 25281595, 
        "old": 24161166
      }, 
      "title": "\uc2e0\ud55c\uad6d\ub2f9", 
      "title_s": "\uc2e0\ud55c\uad6d\ub2f9", 
      "users": 4
    }, 
    {
      "edits": 5, 
      "page_id": 1858856, 
      "rev_ids": {
        "new": 25288425, 
        "old": 25151735
      }, 
      "title": "\ub0e5\ucf54_\ub300\uc804\uc7c1", 
      "title_s": "\ub0e5\ucf54 \ub300\uc804\uc7c1", 
      "users": 2
    }
  ]
}