{
  "date": "August 4, 2022", 
  "fetch_info": {
    "duration": 0.2411959171295166, 
    "end_date": "2022-08-04T08:23:02.112693", 
    "lang": "nn", 
    "start_date": "2022-07-28T08:23:02.112693"
  }, 
  "full_lang_name": "Norwegian (Nynorsk)", 
  "mainspace": [
    {
      "edits": 95, 
      "page_id": 400073, 
      "rev_ids": {
        "new": 3396806, 
        "old": 3396217
      }, 
      "title": "Liste_over_prosjektnummer_for_Russland_sine_marinefart\u00f8y", 
      "title_s": "Liste over prosjektnummer for Russland sine marinefart\u00f8y", 
      "users": 7
    }, 
    {
      "edits": 85, 
      "page_id": 370933, 
      "rev_ids": {
        "new": 3396780, 
        "old": 3395737
      }, 
      "title": "Russiske_marinefart\u00f8y_i_aktiv_teneste", 
      "title_s": "Russiske marinefart\u00f8y i aktiv teneste", 
      "users": 9
    }, 
    {
      "edits": 9, 
      "page_id": 400090, 
      "rev_ids": {
        "new": 3396868, 
        "old": 3396514
      }, 
      "title": "Et_frit_Forhold", 
      "title_s": "Et frit Forhold", 
      "users": 2
    }, 
    {
      "edits": 6, 
      "page_id": 400071, 
      "rev_ids": {
        "new": 3396266, 
        "old": 3396124
      }, 
      "title": "Haseki_sultan", 
      "title_s": "Haseki sultan", 
      "users": 1
    }, 
    {
      "edits": 6, 
      "page_id": 400086, 
      "rev_ids": {
        "new": 3396437, 
        "old": 3396412
      }, 
      "title": "Skapargud", 
      "title_s": "Skapargud", 
      "users": 1
    }, 
    {
      "edits": 5, 
      "page_id": 400113, 
      "rev_ids": {
        "new": 3396890, 
        "old": 3396846
      }, 
      "title": "Festo_eucharistias", 
      "title_s": "Festo eucharistias", 
      "users": 3
    }, 
    {
      "edits": 5, 
      "page_id": 395251, 
      "rev_ids": {
        "new": 3396408, 
        "old": 3395713
      }, 
      "title": "EM_i_fotball_2022_for_kvinner", 
      "title_s": "EM i fotball 2022 for kvinner", 
      "users": 2
    }, 
    {
      "edits": 5, 
      "page_id": 350677, 
      "rev_ids": {
        "new": 3396628, 
        "old": 3395744
      }, 
      "title": "Ub\u00e5tklassen_Yasen", 
      "title_s": "Ub\u00e5tklassen Yasen", 
      "users": 3
    }, 
    {
      "edits": 5, 
      "page_id": 370029, 
      "rev_ids": {
        "new": 3395994, 
        "old": 3159681
      }, 
      "title": "BS-136_\u00abOrenburg\u00bb", 
      "title_s": "BS-136 \u00abOrenburg\u00bb", 
      "users": 2
    }, 
    {
      "edits": 5, 
      "page_id": 259076, 
      "rev_ids": {
        "new": 3396918, 
        "old": 3389970
      }, 
      "title": "Skotsk_musikk", 
      "title_s": "Skotsk musikk", 
      "users": 1
    }, 
    {
      "edits": 4, 
      "page_id": 303049, 
      "rev_ids": {
        "new": 3396530, 
        "old": 3393897
      }, 
      "title": "Friidrett_under_Sommar-OL_2004", 
      "title_s": "Friidrett under Sommar-OL 2004", 
      "users": 1
    }, 
    {
      "edits": 4, 
      "page_id": 144258, 
      "rev_ids": {
        "new": 3396524, 
        "old": 3395755
      }, 
      "title": "Svaler", 
      "title_s": "Svaler", 
      "users": 1
    }, 
    {
      "edits": 4, 
      "page_id": 396358, 
      "rev_ids": {
        "new": 3396709, 
        "old": 3395623
      }, 
      "title": "Grashopper", 
      "title_s": "Grashopper", 
      "users": 1
    }, 
    {
      "edits": 4, 
      "page_id": 400007, 
      "rev_ids": {
        "new": 3396932, 
        "old": 3395251
      }, 
      "title": "Fylkesveg_5829", 
      "title_s": "Fylkesveg 5829", 
      "users": 2
    }, 
    {
      "edits": 4, 
      "page_id": 400049, 
      "rev_ids": {
        "new": 3395831, 
        "old": 3395814
      }, 
      "title": "Sulu\u00f8yane", 
      "title_s": "Sulu\u00f8yane", 
      "users": 1
    }, 
    {
      "edits": 4, 
      "page_id": 142384, 
      "rev_ids": {
        "new": 3396504, 
        "old": 3277018
      }, 
      "title": "Ut_fr\u00e5_Afrika", 
      "title_s": "Ut fr\u00e5 Afrika", 
      "users": 1
    }, 
    {
      "edits": 3, 
      "page_id": 390826, 
      "rev_ids": {
        "new": 3396411, 
        "old": 3395422
      }, 
      "title": "Turban", 
      "title_s": "Turban", 
      "users": 2
    }, 
    {
      "edits": 3, 
      "page_id": 215071, 
      "rev_ids": {
        "new": 3396889, 
        "old": 3350679
      }, 
      "title": "Mons_Litler\u00e9", 
      "title_s": "Mons Litler\u00e9", 
      "users": 2
    }, 
    {
      "edits": 3, 
      "page_id": 77663, 
      "rev_ids": {
        "new": 3396799, 
        "old": 2859685
      }, 
      "title": "New_Horizons", 
      "title_s": "New Horizons", 
      "users": 2
    }, 
    {
      "edits": 3, 
      "page_id": 391590, 
      "rev_ids": {
        "new": 3396849, 
        "old": 3322132
      }, 
      "title": "Jean_Ignace_Isidore_G\u00e9rard_Grandville", 
      "title_s": "Jean Ignace Isidore G\u00e9rard Grandville", 
      "users": 2
    }
  ], 
  "new_articles": [
    {
      "edits": 95, 
      "page_id": 400073, 
      "rev_ids": {
        "new": 3396806, 
        "old": 3396217
      }, 
      "title": "Liste_over_prosjektnummer_for_Russland_sine_marinefart\u00f8y", 
      "title_s": "Liste over prosjektnummer for Russland sine marinefart\u00f8y", 
      "users": 7
    }, 
    {
      "edits": 9, 
      "page_id": 400090, 
      "rev_ids": {
        "new": 3396868, 
        "old": 3396514
      }, 
      "title": "Et_frit_Forhold", 
      "title_s": "Et frit Forhold", 
      "users": 2
    }, 
    {
      "edits": 6, 
      "page_id": 400071, 
      "rev_ids": {
        "new": 3396266, 
        "old": 3396124
      }, 
      "title": "Haseki_sultan", 
      "title_s": "Haseki sultan", 
      "users": 1
    }, 
    {
      "edits": 6, 
      "page_id": 400086, 
      "rev_ids": {
        "new": 3396437, 
        "old": 3396412
      }, 
      "title": "Skapargud", 
      "title_s": "Skapargud", 
      "users": 1
    }, 
    {
      "edits": 5, 
      "page_id": 400113, 
      "rev_ids": {
        "new": 3396890, 
        "old": 3396846
      }, 
      "title": "Festo_eucharistias", 
      "title_s": "Festo eucharistias", 
      "users": 3
    }, 
    {
      "edits": 4, 
      "page_id": 400049, 
      "rev_ids": {
        "new": 3395831, 
        "old": 3395814
      }, 
      "title": "Sulu\u00f8yane", 
      "title_s": "Sulu\u00f8yane", 
      "users": 1
    }, 
    {
      "edits": 3, 
      "page_id": 400061, 
      "rev_ids": {
        "new": 3396732, 
        "old": 3395911
      }, 
      "title": "Kalush", 
      "title_s": "Kalush", 
      "users": 3
    }, 
    {
      "edits": 3, 
      "page_id": 400108, 
      "rev_ids": {
        "new": 3396749, 
        "old": 3396746
      }, 
      "title": "Judith_Weir", 
      "title_s": "Judith Weir", 
      "users": 1
    }, 
    {
      "edits": 3, 
      "page_id": 400115, 
      "rev_ids": {
        "new": 3396888, 
        "old": 3396874
      }, 
      "title": "Bergensdalen_prosti", 
      "title_s": "Bergensdalen prosti", 
      "users": 3
    }, 
    {
      "edits": 3, 
      "page_id": 400117, 
      "rev_ids": {
        "new": 3396935, 
        "old": 3396892
      }, 
      "title": "Dokkehus", 
      "title_s": "Dokkehus", 
      "users": 1
    }
  ], 
  "short_lang_name": "nn", 
  "stats": {
    "anon_edits": 210, 
    "anon_ip_count": 22, 
    "anon_titles": 34, 
    "bot_count": 2, 
    "bot_edits": 14, 
    "bot_titles": 14, 
    "edits": 1021, 
    "titles": 629, 
    "total_users": 86, 
    "users": 64
  }, 
  "talk_stats": {
    "anon_edits": 4, 
    "anon_ip_count": 1, 
    "anon_titles": 1, 
    "bot_count": 1, 
    "bot_edits": 1, 
    "bot_titles": 1, 
    "edits": 17, 
    "titles": 10, 
    "total_users": 8, 
    "users": 7
  }, 
  "talkspace": [
    {
      "edits": 4, 
      "page_id": 400018, 
      "rev_ids": {
        "new": 3395988, 
        "old": 3395467
      }, 
      "title": "Russiske_marinefart\u00f8y_i_aktiv_teneste", 
      "title_s": "Russiske marinefart\u00f8y i aktiv teneste", 
      "users": 2
    }, 
    {
      "edits": 4, 
      "page_id": 370257, 
      "rev_ids": {
        "new": 3396602, 
        "old": 3154170
      }, 
      "title": "Ub\u00e5tklassen_Yasen", 
      "title_s": "Ub\u00e5tklassen Yasen", 
      "users": 1
    }, 
    {
      "edits": 2, 
      "page_id": 98710, 
      "rev_ids": {
        "new": 3395897, 
        "old": 631811
      }, 
      "title": "Omlyd", 
      "title_s": "Omlyd", 
      "users": 2
    }, 
    {
      "edits": 1, 
      "page_id": 9389, 
      "rev_ids": {
        "new": 3396146, 
        "old": 3366380
      }, 
      "title": "Hovudside/Arkiv", 
      "title_s": "Hovudside/Arkiv", 
      "users": 1
    }, 
    {
      "edits": 1, 
      "page_id": 104630, 
      "rev_ids": {
        "new": 3396179, 
        "old": 1301386
      }, 
      "title": "Gerry_Adams", 
      "title_s": "Gerry Adams", 
      "users": 1
    }
  ]
}