{
  "date": "February 6, 2023", 
  "fetch_info": {
    "duration": 2.2166450023651123, 
    "end_date": "2023-02-06T23:05:01.479325", 
    "lang": "fr", 
    "start_date": "2023-01-30T23:05:01.479325"
  }, 
  "full_lang_name": "French", 
  "mainspace": [
    {
      "edits": 302, 
      "page_id": 7256944, 
      "rev_ids": {
        "new": 201157554, 
        "old": 200938108
      }, 
      "title": "\u00c9quipements_de_l'Arm\u00e9e_de_terre_fran\u00e7aise", 
      "title_s": "\u00c9quipements de l'Arm\u00e9e de terre fran\u00e7aise", 
      "users": 92
    }, 
    {
      "edits": 296, 
      "page_id": 3154456, 
      "rev_ids": {
        "new": 201153305, 
        "old": 200937477
      }, 
      "title": "Suzanne_du_Plessis-Belli\u00e8re", 
      "title_s": "Suzanne du Plessis-Belli\u00e8re", 
      "users": 7
    }, 
    {
      "edits": 142, 
      "page_id": 196197, 
      "rev_ids": {
        "new": 201150161, 
        "old": 200637292
      }, 
      "title": "Plouguern\u00e9vel", 
      "title_s": "Plouguern\u00e9vel", 
      "users": 2
    }, 
    {
      "edits": 117, 
      "page_id": 3463945, 
      "rev_ids": {
        "new": 201076474, 
        "old": 200806044
      }, 
      "title": "Coupe_arabe_des_nations_de_basket-ball", 
      "title_s": "Coupe arabe des nations de basket-ball", 
      "users": 6
    }, 
    {
      "edits": 114, 
      "page_id": 13711021, 
      "rev_ids": {
        "new": 201065270, 
        "old": 195350016
      }, 
      "title": "Soufiane_El_Mesrar", 
      "title_s": "Soufiane El Mesrar", 
      "users": 1
    }, 
    {
      "edits": 109, 
      "page_id": 6374394, 
      "rev_ids": {
        "new": 201005531, 
        "old": 200015151
      }, 
      "title": "\u00c9quipe_du_Maroc_de_futsal_FIFA", 
      "title_s": "\u00c9quipe du Maroc de futsal FIFA", 
      "users": 1
    }, 
    {
      "edits": 106, 
      "page_id": 181584, 
      "rev_ids": {
        "new": 201155984, 
        "old": 200935287
      }, 
      "title": "Basiliscus", 
      "title_s": "Basiliscus", 
      "users": 1
    }, 
    {
      "edits": 104, 
      "page_id": 5572308, 
      "rev_ids": {
        "new": 201153515, 
        "old": 200911949
      }, 
      "title": "Agence_centrale_de_presse", 
      "title_s": "Agence centrale de presse", 
      "users": 2
    }, 
    {
      "edits": 103, 
      "page_id": 132170, 
      "rev_ids": {
        "new": 201146116, 
        "old": 199202404
      }, 
      "title": "Annie_Hall", 
      "title_s": "Annie Hall", 
      "users": 4
    }, 
    {
      "edits": 100, 
      "page_id": 1390407, 
      "rev_ids": {
        "new": 201153905, 
        "old": 199248956
      }, 
      "title": "Providence_(religion)", 
      "title_s": "Providence (religion)", 
      "users": 4
    }, 
    {
      "edits": 100, 
      "page_id": 11581635, 
      "rev_ids": {
        "new": 201128967, 
        "old": 200928462
      }, 
      "title": "Mus\u00e9e_du_domaine_royal_de_Marly", 
      "title_s": "Mus\u00e9e du domaine royal de Marly", 
      "users": 14
    }, 
    {
      "edits": 96, 
      "page_id": 12489050, 
      "rev_ids": {
        "new": 201136734, 
        "old": 194077770
      }, 
      "title": "Hi\u00e9rarchie_dans_l'\u00c9glise_catholique", 
      "title_s": "Hi\u00e9rarchie dans l'\u00c9glise catholique", 
      "users": 5
    }, 
    {
      "edits": 94, 
      "page_id": 15444613, 
      "rev_ids": {
        "new": 201158421, 
        "old": 201133722
      }, 
      "title": "S\u00e9isme_de_2023_en_Turquie_et_Syrie", 
      "title_s": "S\u00e9isme de 2023 en Turquie et Syrie", 
      "users": 27
    }, 
    {
      "edits": 93, 
      "page_id": 195881, 
      "rev_ids": {
        "new": 201098610, 
        "old": 200928054
      }, 
      "title": "Kergrist-Mo\u00eblou", 
      "title_s": "Kergrist-Mo\u00eblou", 
      "users": 4
    }, 
    {
      "edits": 91, 
      "page_id": 5107198, 
      "rev_ids": {
        "new": 201159446, 
        "old": 200838588
      }, 
      "title": "Drapeau_de_la_Martinique", 
      "title_s": "Drapeau de la Martinique", 
      "users": 17
    }, 
    {
      "edits": 91, 
      "page_id": 648629, 
      "rev_ids": {
        "new": 201085059, 
        "old": 199830665
      }, 
      "title": "Sophie_de_Prusse", 
      "title_s": "Sophie de Prusse", 
      "users": 1
    }, 
    {
      "edits": 91, 
      "page_id": 15397528, 
      "rev_ids": {
        "new": 201156959, 
        "old": 200926597
      }, 
      "title": "Projet_de_r\u00e9forme_des_retraites_en_France_en_2023", 
      "title_s": "Projet de r\u00e9forme des retraites en France en 2023", 
      "users": 17
    }, 
    {
      "edits": 89, 
      "page_id": 1169638, 
      "rev_ids": {
        "new": 201133477, 
        "old": 199544991
      }, 
      "title": "Vikidia", 
      "title_s": "Vikidia", 
      "users": 1
    }, 
    {
      "edits": 86, 
      "page_id": 25215, 
      "rev_ids": {
        "new": 201145931, 
        "old": 199691612
      }, 
      "title": "Ordre_souverain_militaire_et_hospitalier_de_Saint-Jean_de_J\u00e9rusalem,_de_Rhodes_et_de_Malte", 
      "title_s": "Ordre souverain militaire et hospitalier de Saint-Jean de J\u00e9rusalem, de Rhodes et de Malte", 
      "users": 3
    }, 
    {
      "edits": 83, 
      "page_id": 14991858, 
      "rev_ids": {
        "new": 201148908, 
        "old": 200900133
      }, 
      "title": "Championnat_d'Allemagne_de_football_2022-2023", 
      "title_s": "Championnat d'Allemagne de football 2022-2023", 
      "users": 2
    }
  ], 
  "new_articles": [
    {
      "edits": 94, 
      "page_id": 15444613, 
      "rev_ids": {
        "new": 201158421, 
        "old": 201133722
      }, 
      "title": "Tremblement_de_terre_en_Turquie_et_Syrie_en_2023", 
      "title_s": "Tremblement de terre en Turquie et Syrie en 2023", 
      "users": 27
    }, 
    {
      "edits": 78, 
      "page_id": 15432980, 
      "rev_ids": {
        "new": 201155471, 
        "old": 200951502
      }, 
      "title": "Place_Saint-Roch_(Mont-de-Marsan)", 
      "title_s": "Place Saint-Roch (Mont-de-Marsan)", 
      "users": 2
    }, 
    {
      "edits": 77, 
      "page_id": 15442628, 
      "rev_ids": {
        "new": 201159026, 
        "old": 201102907
      }, 
      "title": "Coupe_nationale_des_quartiers", 
      "title_s": "Coupe nationale des quartiers", 
      "users": 12
    }, 
    {
      "edits": 73, 
      "page_id": 15434083, 
      "rev_ids": {
        "new": 201159103, 
        "old": 200967991
      }, 
      "title": "John_Mangefel", 
      "title_s": "John Mangefel", 
      "users": 4
    }, 
    {
      "edits": 61, 
      "page_id": 15435195, 
      "rev_ids": {
        "new": 201083752, 
        "old": 200986695
      }, 
      "title": "Pierre_Le_Mardele", 
      "title_s": "Pierre Le Mardele", 
      "users": 4
    }, 
    {
      "edits": 58, 
      "page_id": 15437006, 
      "rev_ids": {
        "new": 201132131, 
        "old": 201014198
      }, 
      "title": "Meurtre_de_Sihem_Belouahmia", 
      "title_s": "Meurtre de Sihem Belouahmia", 
      "users": 11
    }, 
    {
      "edits": 54, 
      "page_id": 15440489, 
      "rev_ids": {
        "new": 201132354, 
        "old": 201067412
      }, 
      "title": "Charles_Wambst", 
      "title_s": "Charles Wambst", 
      "users": 3
    }, 
    {
      "edits": 53, 
      "page_id": 15432077, 
      "rev_ids": {
        "new": 201102223, 
        "old": 200938419
      }, 
      "title": "Etsak\u1ecd_au_Nigeria", 
      "title_s": "Etsak\u1ecd au Nigeria", 
      "users": 5
    }, 
    {
      "edits": 52, 
      "page_id": 15441070, 
      "rev_ids": {
        "new": 201150758, 
        "old": 201075651
      }, 
      "title": "Renaissance_de_l'eau-forte", 
      "title_s": "Renaissance de l'eau-forte", 
      "users": 3
    }, 
    {
      "edits": 44, 
      "page_id": 15441662, 
      "rev_ids": {
        "new": 201155105, 
        "old": 201084948
      }, 
      "title": "Incident_des_ballons_chinois_de_2023", 
      "title_s": "Incident des ballons chinois de 2023", 
      "users": 12
    }
  ], 
  "short_lang_name": "fr", 
  "stats": {
    "anon_edits": 19659, 
    "anon_ip_count": 8123, 
    "anon_titles": 11067, 
    "bot_count": 15, 
    "bot_edits": 5399, 
    "bot_titles": 4997, 
    "edits": 143385, 
    "titles": 71248, 
    "total_users": 22449, 
    "users": 14326
  }, 
  "talk_stats": {
    "anon_edits": 299, 
    "anon_ip_count": 235, 
    "anon_titles": 227, 
    "bot_count": 7, 
    "bot_edits": 796, 
    "bot_titles": 686, 
    "edits": 8648, 
    "titles": 5066, 
    "total_users": 1198, 
    "users": 963
  }, 
  "talkspace": [
    {
      "edits": 309, 
      "page_id": 856918, 
      "rev_ids": {
        "new": 201158466, 
        "old": 200936673
      }, 
      "title": "Informaticien", 
      "title_s": "Informaticien", 
      "users": 29
    }, 
    {
      "edits": 88, 
      "page_id": 11837940, 
      "rev_ids": {
        "new": 201158968, 
        "old": 200903051
      }, 
      "title": "Liste_de_familles_subsistantes_d'ancienne_bourgeoisie_fran\u00e7aise", 
      "title_s": "Liste de familles subsistantes d'ancienne bourgeoisie fran\u00e7aise", 
      "users": 8
    }, 
    {
      "edits": 71, 
      "page_id": 15133379, 
      "rev_ids": {
        "new": 201060981, 
        "old": 196272614
      }, 
      "title": "Troubles_pro-russes_de_2014_en_Ukraine", 
      "title_s": "Troubles pro-russes de 2014 en Ukraine", 
      "users": 7
    }, 
    {
      "edits": 69, 
      "page_id": 15398898, 
      "rev_ids": {
        "new": 201157836, 
        "old": 200929519
      }, 
      "title": "Droite_hors_les_murs", 
      "title_s": "Droite hors les murs", 
      "users": 5
    }, 
    {
      "edits": 53, 
      "page_id": 15422598, 
      "rev_ids": {
        "new": 201115702, 
        "old": 200870854
      }, 
      "title": "\u00c9lisabeth_Tible/Bon_article", 
      "title_s": "\u00c9lisabeth Tible/Bon article", 
      "users": 14
    }
  ]
}