{
  "date": "November 1, 2019", 
  "fetch_info": {
    "duration": 14.071705102920532, 
    "end_date": "2019-11-01T13:00:09.402455", 
    "lang": "ko", 
    "start_date": "2019-10-25T13:00:09.402455"
  }, 
  "full_lang_name": "Korean", 
  "mainspace": [
    {
      "edits": 137, 
      "page_id": 1726490, 
      "rev_ids": {
        "new": 25142495, 
        "old": 25108182
      }, 
      "title": "2019\ub144_FIFA_U-17_\uc6d4\ub4dc\ucef5", 
      "title_s": "2019\ub144 FIFA U-17 \uc6d4\ub4dc\ucef5", 
      "users": 7
    }, 
    {
      "edits": 134, 
      "page_id": 1303148, 
      "rev_ids": {
        "new": 25143991, 
        "old": 25060749
      }, 
      "title": "\ubaac\uc2a4\ud0c0\uc5d1\uc2a4", 
      "title_s": "\ubaac\uc2a4\ud0c0\uc5d1\uc2a4", 
      "users": 35
    }, 
    {
      "edits": 111, 
      "page_id": 2455306, 
      "rev_ids": {
        "new": 25143576, 
        "old": 25110474
      }, 
      "title": "\uc2a4\ud2b8\ub808\uc774_\ud0a4\uc988\uc758_\uc74c\ubc18_\uc678_\ud65c\ub3d9_\ubaa9\ub85d", 
      "title_s": "\uc2a4\ud2b8\ub808\uc774 \ud0a4\uc988\uc758 \uc74c\ubc18 \uc678 \ud65c\ub3d9 \ubaa9\ub85d", 
      "users": 1
    }, 
    {
      "edits": 95, 
      "page_id": 2380671, 
      "rev_ids": {
        "new": 25113845, 
        "old": 24864820
      }, 
      "title": "2019\ub144_\ub3d9\ud0dc\ud3c9\uc591_\ud5c8\ub9ac\ucf00\uc778", 
      "title_s": "2019\ub144 \ub3d9\ud0dc\ud3c9\uc591 \ud5c8\ub9ac\ucf00\uc778", 
      "users": 3
    }, 
    {
      "edits": 91, 
      "page_id": 2353935, 
      "rev_ids": {
        "new": 25140439, 
        "old": 25105739
      }, 
      "title": "UEFA_\uc5ec\uc790_\uc720\ub85c_2021_\uc608\uc120", 
      "title_s": "UEFA \uc5ec\uc790 \uc720\ub85c 2021 \uc608\uc120", 
      "users": 4
    }, 
    {
      "edits": 86, 
      "page_id": 2551600, 
      "rev_ids": {
        "new": 25143869, 
        "old": 25108114
      }, 
      "title": "\uc6b0\uc544\ud55c_\ubaa8\ub140", 
      "title_s": "\uc6b0\uc544\ud55c \ubaa8\ub140", 
      "users": 28
    }, 
    {
      "edits": 81, 
      "page_id": 2577983, 
      "rev_ids": {
        "new": 25143879, 
        "old": 25110414
      }, 
      "title": "\ud55c\ubc88_\ub2e4\ub140\uc654\uc2b5\ub2c8\ub2e4", 
      "title_s": "\ud55c\ubc88 \ub2e4\ub140\uc654\uc2b5\ub2c8\ub2e4", 
      "users": 13
    }, 
    {
      "edits": 62, 
      "page_id": 1804345, 
      "rev_ids": {
        "new": 25143814, 
        "old": 25061618
      }, 
      "title": "\uacf5\ub8e1\uba54\uce74\ub4dc", 
      "title_s": "\uacf5\ub8e1\uba54\uce74\ub4dc", 
      "users": 10
    }, 
    {
      "edits": 62, 
      "page_id": 2307556, 
      "rev_ids": {
        "new": 25143983, 
        "old": 25109840
      }, 
      "title": "\ubc30\uac00\ubcf8\ub4dc_(\ub4dc\ub77c\ub9c8)", 
      "title_s": "\ubc30\uac00\ubcf8\ub4dc (\ub4dc\ub77c\ub9c8)", 
      "users": 22
    }, 
    {
      "edits": 61, 
      "page_id": 1804519, 
      "rev_ids": {
        "new": 25143386, 
        "old": 25110379
      }, 
      "title": "\ucd08\uc774\ub77d\ucee8\ud150\uce20\ud329\ud1a0\ub9ac", 
      "title_s": "\ucd08\uc774\ub77d\ucee8\ud150\uce20\ud329\ud1a0\ub9ac", 
      "users": 11
    }, 
    {
      "edits": 58, 
      "page_id": 68215, 
      "rev_ids": {
        "new": 25142781, 
        "old": 25091858
      }, 
      "title": "\uae40\uc885\ubbfc", 
      "title_s": "\uae40\uc885\ubbfc", 
      "users": 7
    }, 
    {
      "edits": 57, 
      "page_id": 1455928, 
      "rev_ids": {
        "new": 25143781, 
        "old": 25108716
      }, 
      "title": "\ud074\ub798\uc2dc_\ub85c\uc584", 
      "title_s": "\ud074\ub798\uc2dc \ub85c\uc584", 
      "users": 18
    }, 
    {
      "edits": 54, 
      "page_id": 1246909, 
      "rev_ids": {
        "new": 25137530, 
        "old": 25110528
      }, 
      "title": "\ubbf8\uc2a4\ud130\ub9ac_\uc74c\uc545\uc1fc_\ubcf5\uba74\uac00\uc655", 
      "title_s": "\ubbf8\uc2a4\ud130\ub9ac \uc74c\uc545\uc1fc \ubcf5\uba74\uac00\uc655", 
      "users": 8
    }, 
    {
      "edits": 53, 
      "page_id": 2579089, 
      "rev_ids": {
        "new": 25134516, 
        "old": 25110572
      }, 
      "title": "2019\ub144_\ud55c\uad6d\uc2dc\ub9ac\uc988", 
      "title_s": "2019\ub144 \ud55c\uad6d\uc2dc\ub9ac\uc988", 
      "users": 5
    }, 
    {
      "edits": 52, 
      "page_id": 2569039, 
      "rev_ids": {
        "new": 25142070, 
        "old": 25108319
      }, 
      "title": "\uaf43\uae38\ub9cc_\uac78\uc5b4\uc694", 
      "title_s": "\uaf43\uae38\ub9cc \uac78\uc5b4\uc694", 
      "users": 16
    }, 
    {
      "edits": 51, 
      "page_id": 117861, 
      "rev_ids": {
        "new": 25143281, 
        "old": 25099778
      }, 
      "title": "\uc11c\uc6b8\uad50\ud1b5\uacf5\uc0ac_2000\ud638\ub300_\ucd08\ud37c\uc81c\uc5b4_\uc804\ub3d9\ucc28", 
      "title_s": "\uc11c\uc6b8\uad50\ud1b5\uacf5\uc0ac 2000\ud638\ub300 \ucd08\ud37c\uc81c\uc5b4 \uc804\ub3d9\ucc28", 
      "users": 9
    }, 
    {
      "edits": 50, 
      "page_id": 243956, 
      "rev_ids": {
        "new": 25143655, 
        "old": 25094038
      }, 
      "title": "\uc815\uc7ac\ud615", 
      "title_s": "\uc815\uc7ac\ud615", 
      "users": 1
    }, 
    {
      "edits": 48, 
      "page_id": 89989, 
      "rev_ids": {
        "new": 25143452, 
        "old": 25108422
      }, 
      "title": "KBS_2TV", 
      "title_s": "KBS 2TV", 
      "users": 10
    }, 
    {
      "edits": 48, 
      "page_id": 2034402, 
      "rev_ids": {
        "new": 25139727, 
        "old": 25109896
      }, 
      "title": "\ub3c4\ud2f0", 
      "title_s": "\ub3c4\ud2f0", 
      "users": 9
    }, 
    {
      "edits": 47, 
      "page_id": 2503840, 
      "rev_ids": {
        "new": 25143253, 
        "old": 25098392
      }, 
      "title": "\uc870\uc120\ub85c\ucf54_-_\ub179\ub450\uc804", 
      "title_s": "\uc870\uc120\ub85c\ucf54 - \ub179\ub450\uc804", 
      "users": 11
    }
  ], 
  "new_articles": [
    {
      "edits": 39, 
      "page_id": 2588771, 
      "rev_ids": {
        "new": 25125250, 
        "old": 25111639
      }, 
      "title": "\uc870\uac15\uc81c", 
      "title_s": "\uc870\uac15\uc81c", 
      "users": 2
    }, 
    {
      "edits": 27, 
      "page_id": 2590771, 
      "rev_ids": {
        "new": 25143657, 
        "old": 25133907
      }, 
      "title": "\uc2a4\ud53c\uc5b4\ub9cc_\ube0c\ub77c\uc6b4_\uacf5\uc2dd", 
      "title_s": "\uc2a4\ud53c\uc5b4\ub9cc \ube0c\ub77c\uc6b4 \uacf5\uc2dd", 
      "users": 2
    }, 
    {
      "edits": 25, 
      "page_id": 2590964, 
      "rev_ids": {
        "new": 25137551, 
        "old": 25136269
      }, 
      "title": "\ucfe0\ud504_\ub4dc_\ub77c_\ub9ac\uadf8_2019-20", 
      "title_s": "\ucfe0\ud504 \ub4dc \ub77c \ub9ac\uadf8 2019-20", 
      "users": 1
    }, 
    {
      "edits": 22, 
      "page_id": 2589033, 
      "rev_ids": {
        "new": 25115300, 
        "old": 25113250
      }, 
      "title": "\uae40\ud604\ubaa9", 
      "title_s": "\uae40\ud604\ubaa9", 
      "users": 1
    }, 
    {
      "edits": 21, 
      "page_id": 2589743, 
      "rev_ids": {
        "new": 25140636, 
        "old": 25121151
      }, 
      "title": "\ubc14\ub9ac\uc0e4_\uae30\uc2b5", 
      "title_s": "\ubc14\ub9ac\uc0e4 \uae30\uc2b5", 
      "users": 6
    }, 
    {
      "edits": 17, 
      "page_id": 2589418, 
      "rev_ids": {
        "new": 25137088, 
        "old": 25117016
      }, 
      "title": "\ubc15\uc131\uc724", 
      "title_s": "\ubc15\uc131\uc724", 
      "users": 3
    }, 
    {
      "edits": 16, 
      "page_id": 2588703, 
      "rev_ids": {
        "new": 25111471, 
        "old": 25111279
      }, 
      "title": "\uc190\uc2dc\ud5cc_(1923\ub144)", 
      "title_s": "\uc190\uc2dc\ud5cc (1923\ub144)", 
      "users": 1
    }, 
    {
      "edits": 15, 
      "page_id": 2589602, 
      "rev_ids": {
        "new": 25143637, 
        "old": 25119321
      }, 
      "title": "\uc548\ub4dc\ub85c\uc774\ub4dc_10", 
      "title_s": "\uc548\ub4dc\ub85c\uc774\ub4dc 10", 
      "users": 4
    }, 
    {
      "edits": 15, 
      "page_id": 2590680, 
      "rev_ids": {
        "new": 25143709, 
        "old": 25132843
      }, 
      "title": "\uc874_\uae38", 
      "title_s": "\uc874 \uae38", 
      "users": 2
    }, 
    {
      "edits": 14, 
      "page_id": 2590653, 
      "rev_ids": {
        "new": 25132558, 
        "old": 25132379
      }, 
      "title": "\ud558\ub098\ub2d8\uc758_\uc190", 
      "title_s": "\ud558\ub098\ub2d8\uc758 \uc190", 
      "users": 1
    }
  ], 
  "short_lang_name": "ko", 
  "stats": {
    "anon_edits": 10737, 
    "anon_ip_count": 2123, 
    "anon_titles": 4500, 
    "bot_count": 17, 
    "bot_edits": 3102, 
    "bot_titles": 2754, 
    "edits": 24894, 
    "titles": 11654, 
    "total_users": 4981, 
    "users": 2858
  }, 
  "talk_stats": {
    "anon_edits": 34, 
    "anon_ip_count": 15, 
    "anon_titles": 10, 
    "bot_count": 5, 
    "bot_edits": 702, 
    "bot_titles": 699, 
    "edits": 848, 
    "titles": 750, 
    "total_users": 70, 
    "users": 55
  }, 
  "talkspace": [
    {
      "edits": 26, 
      "page_id": 315602, 
      "rev_ids": {
        "new": 25129141, 
        "old": 25096100
      }, 
      "title": "\uc120\ube44_(\ubbfc\uc871)", 
      "title_s": "\uc120\ube44 (\ubbfc\uc871)", 
      "users": 7
    }, 
    {
      "edits": 23, 
      "page_id": 393913, 
      "rev_ids": {
        "new": 25123436, 
        "old": 25109596
      }, 
      "title": "\uc804\uc790\uc0ac\uc804\uacfc_\uc0ac\uc804\ud3b8\ucc2c", 
      "title_s": "\uc804\uc790\uc0ac\uc804\uacfc \uc0ac\uc804\ud3b8\ucc2c", 
      "users": 3
    }, 
    {
      "edits": 10, 
      "page_id": 1246303, 
      "rev_ids": {
        "new": 25138050, 
        "old": 24535452
      }, 
      "title": "\uace0\uc591\uc774_\ud3a0\ub9ad\uc2a4", 
      "title_s": "\uace0\uc591\uc774 \ud3a0\ub9ad\uc2a4", 
      "users": 3
    }, 
    {
      "edits": 8, 
      "page_id": 2584523, 
      "rev_ids": {
        "new": 25124150, 
        "old": 25108057
      }, 
      "title": "\uc724\ub0b4\ud604", 
      "title_s": "\uc724\ub0b4\ud604", 
      "users": 2
    }, 
    {
      "edits": 8, 
      "page_id": 92498, 
      "rev_ids": {
        "new": 25120770, 
        "old": 21729555
      }, 
      "title": "\ub300\ud55c\ubbfc\uad6d_\uac80\ucc30\uccad", 
      "title_s": "\ub300\ud55c\ubbfc\uad6d \uac80\ucc30\uccad", 
      "users": 6
    }
  ]
}